readabledelta2/__init__.py
readabledelta2/__version__.py
readabledelta2/py.typed
readabledelta2/readabledelta.py
readabledelta2-0.0.2.dist-info/LICENSE
readabledelta2-0.0.2.dist-info/METADATA
readabledelta2-0.0.2.dist-info/WHEEL
readabledelta2-0.0.2.dist-info/RECORD
