Metadata-Version: 2.1
Name: readabledelta2
Version: 0.0.2
Summary: 
Home-page: https://github.com/bandophahita/readabledelta2
License: MIT
Author: Marcel Wilson
Author-email: trenchrats@gmail.com
Requires-Python: >=3.10,<4.0
Classifier: Development Status :: 5 - Production/Stable
Classifier: Intended Audience :: Developers
Classifier: License :: OSI Approved :: MIT License
Classifier: Natural Language :: English
Classifier: Operating System :: OS Independent
Classifier: Programming Language :: Python :: 3
Classifier: Programming Language :: Python :: 3.10
Classifier: Programming Language :: Python :: 3.11
Classifier: Programming Language :: Python :: 3.12
Classifier: Programming Language :: Python :: 3 :: Only
Classifier: Topic :: Software Development :: Quality Assurance
Classifier: Topic :: Software Development :: Testing
Classifier: Topic :: Software Development :: Testing :: BDD
Provides-Extra: dev
Provides-Extra: test
Requires-Dist: black ; extra == "dev"
Requires-Dist: coverage ; extra == "dev" or extra == "test"
Requires-Dist: mypy ; extra == "dev"
Requires-Dist: pytest ; extra == "dev" or extra == "test"
Requires-Dist: pytest-mock ; extra == "dev" or extra == "test"
Requires-Dist: python-dateutil
Requires-Dist: ruff (>=0.2.0) ; extra == "dev"
Requires-Dist: tox ; extra == "dev"
Requires-Dist: types-python-dateutil ; extra == "dev"
Project-URL: Repository, https://github.com/bandophahita/readabledelta2
